sdft/__init__.py
sdft/ksdft.py
sdft/sdft.py
sdft/stft.py
sdft-1.4.dist-info/LICENSE
sdft-1.4.dist-info/METADATA
sdft-1.4.dist-info/WHEEL
sdft-1.4.dist-info/top_level.txt
sdft-1.4.dist-info/RECORD
